proml/__init__.py
proml/asgi.py
proml/settings.py
proml/skeleton.py
proml/urls.py
proml/wsgi.py
proml-0.0.1.dist-info/AUTHORS.rst
proml-0.0.1.dist-info/LICENSE.txt
proml-0.0.1.dist-info/METADATA
proml-0.0.1.dist-info/WHEEL
proml-0.0.1.dist-info/top_level.txt
proml-0.0.1.dist-info/RECORD
